tsugu/__init__.py
tsugu/__main__.py
tsugu/alc_cmd.py
tsugu/config.py
tsugu/const.py
tsugu-6.4.1.dist-info/LICENSE
tsugu-6.4.1.dist-info/METADATA
tsugu-6.4.1.dist-info/WHEEL
tsugu-6.4.1.dist-info/entry_points.txt
tsugu-6.4.1.dist-info/top_level.txt
tsugu-6.4.1.dist-info/RECORD
