Metadata-Version: 2.1
Name: tsugu
Version: 6.4.1
Summary: Tsugu Python Frontend
Home-page: https://github.com/kumoSleeping/ChatTsuguPy
Author: kumoSleeping
Author-email: zjr2992@outlook.com
License: MIT
Platform: UNKNOWN
Classifier: Programming Language :: Python :: 3.8
Classifier: License :: OSI Approved :: MIT License
Classifier: Operating System :: OS Independent
Requires-Python: >=3.8
Requires-Dist: loguru
Requires-Dist: python-dotenv
Requires-Dist: tsugu-api-python[httpx]>=1.5.10
Requires-Dist: arclet-alconna<2.0.0a1
